osgeo_manager/__init__.py
osgeo_manager/apps.py
osgeo_manager/base_manager.py
osgeo_manager/config.py
osgeo_manager/constants.py
osgeo_manager/decorators.py
osgeo_manager/exceptions.py
osgeo_manager/layers.py
osgeo_manager/log.py
osgeo_manager/mixins.py
osgeo_manager/os_utils.py
osgeo_manager/publishers.py
osgeo_manager/styles.py
osgeo_manager/utils.py
osgeo_manager-0.2.0.dist-info/LICENSE
osgeo_manager-0.2.0.dist-info/METADATA
osgeo_manager-0.2.0.dist-info/WHEEL
osgeo_manager-0.2.0.dist-info/dependency_links.txt
osgeo_manager-0.2.0.dist-info/top_level.txt
osgeo_manager-0.2.0.dist-info/RECORD
